kvo/datesmcp/__init__.py
kvo/datesmcp/cli.py
kvo/datesmcp/clioptions.py
kvo/datesmcp/mcptools.py
kvo_dates_mcp-0.1.0.dist-info/METADATA
kvo_dates_mcp-0.1.0.dist-info/WHEEL
kvo_dates_mcp-0.1.0.dist-info/licenses/LICENSE
kvo_dates_mcp-0.1.0.dist-info/RECORD
